pyhagl/__init__.py
pyhagl/base_functions.py
pyhagl/base_types.py
pyhagl/composition_types.py
pyhagl/enum_type.py
pyhagl/exceptions.py
pyhagl/functions.py
pyhagl/limits.py
pyhagl/physic_types.py
pyhagl/proxy.py
pyhagl/python_types.py
pyhagl/straight_type.py
pyhagl/template.py
pyhagl/wrapper.py
pyhagl-0.0.1.dist-info/LICENSE
pyhagl-0.0.1.dist-info/WHEEL
pyhagl-0.0.1.dist-info/METADATA
pyhagl-0.0.1.dist-info/RECORD
