Metadata-Version: 2.1
Name: pyhagl
Version: 0.0.1
Summary: Library to describe Gymnasium spaces as Python objects
Author: TheShenk
Requires-Python: >=3.8
Classifier: Programming Language :: Python :: 3
Classifier: License :: OSI Approved :: MIT License
Requires-Dist: gymnasium
Requires-Dist: numpy
Requires-Dist: pytest >=2.7.3 ; extra == "test"
Requires-Dist: pytest-cov ; extra == "test"
Requires-Dist: pettingzoo ; extra == "wrappers"
Project-URL: Homepage, https://github.com/TheShenk/hai-nonconflict-action-learning
Project-URL: Issues, https://github.com/TheShenk/hai-nonconflict-action-learning/issues
Provides-Extra: test
Provides-Extra: wrappers
